{
    "labs": [
        {
            "ces.ipynb": "ces"
        },
        {
            "一、python是什么.ipynb": "一、python是什么"
        },
        {
            "七、对象.ipynb": "七、对象"
        },
        {
            "三、基本语法.ipynb": "三、基本语法"
        },
        {
            "二、第一个python程序.ipynb": "二、第一个python程序"
        },
        {
            "五、高级特性.ipynb": "五、高级特性"
        },
        {
            "六、模块.ipynb": "六、模块"
        },
        {
            "四、函数.ipynb": "四、函数"
        }
    ]
}